kcolours/__init__.py
kcolours/__main__.py
kcolours/cli.py
kcolours/colours.py
kcolours-1.0.3.dist-info/licenses/LICENSE.md
kcolours-1.0.3.dist-info/METADATA
kcolours-1.0.3.dist-info/WHEEL
kcolours-1.0.3.dist-info/entry_points.txt
kcolours-1.0.3.dist-info/top_level.txt
kcolours-1.0.3.dist-info/RECORD
