Metadata-Version: 2.4
Name: kcolours
Version: 1.0.3
Summary: CLI tool to extract a colour palette from an image using k-means clustering.
Author-email: Chloe Fisher <dev@chlofisher.com>
License: MIT License
Requires-Python: >=3.13
License-File: LICENSE.md
Requires-Dist: click>=8.2.1
Requires-Dist: imageio>=2.37.0
Requires-Dist: numpy>=2.3.1
Requires-Dist: rich>=14.0.0
Requires-Dist: scikit-image>=0.25.2
Requires-Dist: scipy>=1.16.0
Dynamic: license-file
